MANIFEST.in
readme.rst
setup.py
MailSender.egg-info/PKG-INFO
MailSender.egg-info/SOURCES.txt
MailSender.egg-info/dependency_links.txt
MailSender.egg-info/not-zip-safe
MailSender.egg-info/top_level.txt
mailsender/__init__.py