Metadata-Version: 1.0
Name: MailSender
Version: 0.0.2
Summary: a class used to send mail by smtp
Home-page: UNKNOWN
Author: justy
Author-email: justyfox@gmail.com
License: BSD
Platform: UNKNOWN
Classifier: Development Status :: 2 - Pre-Alpha
Classifier: Environment :: Console
Classifier: Intended Audience :: Developers
Classifier: Intended Audience :: System Administrators
Classifier: License :: OSI Approved :: BSD License
Classifier: Operating System :: OS Independent
Classifier: Programming Language :: Python
